<?xml version = '1.0' encoding = 'UTF-8' standalone = 'yes'?>
<?xml-stylesheet href='capatomproduct.xsl' type='text/xsl'?>

<!--
This atom/xml feed is an index to active advisories, watches and warnings 
issued by the National Weather Service.  This index file is not the complete 
Common Alerting Protocol (CAP) alert message.  To obtain the complete CAP 
alert, please follow the links for each entry in this index.  Also note the 
CAP message uses a style sheet to convey the information in a human readable 
format.  Please view the source of the CAP message to see the complete data 
set.  Not all information in the CAP message is contained in this index of 
active alerts.
-->

<alert xmlns = 'urn:oasis:names:tc:emergency:cap:1.1'>

<!-- http-date = Tue, 17 Jan 2023 04:54:00 GMT -->
<identifier>NOAA-NWS-ALERTS-CO126630F0B498.WinterStormWatch.1266310F7220CO.GLDWSWGLD.0f95121f8c25e40cb4ca2f94d85ea103</identifier>
<sender>w-nws.webmaster@noaa.gov</sender>
<sent>2023-01-16T21:54:00-07:00</sent>
<status>Actual</status>
<msgType>Alert</msgType>
<scope>Public</scope>
<note>Alert for Kit Carson County (Colorado) Issued by the National Weather Service</note>
<info>
<category>Met</category>
<event>Winter Storm Watch</event>
<urgency>Future</urgency>
<severity>Moderate</severity>
<certainty>Possible</certainty>
<eventCode>
<valueName>SAME</valueName>
<value>WSA</value>
</eventCode>
<effective>2023-01-17T17:00:00-07:00</effective>
<expires>2023-01-18T23:00:00-07:00</expires>
<senderName>NWS Goodland (Northwestern Kansas and East Central Colorado)</senderName>
<headline>Winter Storm Watch issued January 16 at 9:54PM MST until January 18 at 11:00PM MST by NWS Goodland</headline>
<description>...WINTER STORM WATCH REMAINS IN EFFECT FROM TUESDAY AFTERNOON
THROUGH WEDNESDAY EVENING...
* WHAT...Heavy wet snow. Snow accumulations greater than 6
inches possible.
* WHERE...Portions of east central Colorado and northwest Kansas,
mainly along and north of Interstate 70.
* WHEN...From Tuesday evening through Wednesday night.
* IMPACTS...Travel could be very difficult. The hazardous
conditions could impact the morning or evening commute.</description>
<instruction>Monitor the latest forecasts for updates on this situation.</instruction>
<parameter>
<valueName>WMOHEADER</valueName>
<value></value>
</parameter>
<parameter>
<valueName>UGC</valueName>
<value>COZ091-KSZ001>004-013>016</value>
</parameter>
<parameter>
<valueName>VTEC</valueName>
<value>/O.CON.KGLD.WS.A.0001.230118T0000Z-230119T0600Z/</value>
</parameter>
<parameter>
<valueName>TIME...MOT...LOC</valueName>
<value></value>
</parameter>
<area>
<areaDesc>Kit Carson County</areaDesc>
<polygon></polygon>
<geocode>
<valueName>FIPS6</valueName>
<value>008063</value>
</geocode>
<geocode>
<valueName>UGC</valueName>
<value>COZ091</value>
</geocode>
</area>
</info>
</alert>