<?xml version = '1.0' encoding = 'UTF-8' standalone = 'yes'?>
<?xml-stylesheet href='capatomproduct.xsl' type='text/xsl'?>

<!--
This atom/xml feed is an index to active advisories, watches and warnings 
issued by the National Weather Service.  This index file is not the complete 
Common Alerting Protocol (CAP) alert message.  To obtain the complete CAP 
alert, please follow the links for each entry in this index.  Also note the 
CAP message uses a style sheet to convey the information in a human readable 
format.  Please view the source of the CAP message to see the complete data 
set.  Not all information in the CAP message is contained in this index of 
active alerts.
-->

<alert xmlns = 'urn:oasis:names:tc:emergency:cap:1.1'>

<!-- http-date = Sun, 09 Jul 2023 06:59:00 GMT -->
<identifier>NOAA-NWS-ALERTS-MD1266543A38AC.FloodWatch.12665448C7A0MD.PHIFFAPHI.9ce11316199144cc612a6865b31a3354</identifier>
<sender>w-nws.webmaster@noaa.gov</sender>
<sent>2023-07-09T02:59:00-04:00</sent>
<status>Actual</status>
<msgType>Alert</msgType>
<scope>Public</scope>
<note>Alert for Caroline; Talbot (Maryland) Issued by the National Weather Service</note>
<info>
<category>Met</category>
<event>Flood Watch</event>
<urgency>Future</urgency>
<severity>Moderate</severity>
<certainty>Possible</certainty>
<eventCode>
<valueName>SAME</valueName>
<value>FLA</value>
</eventCode>
<effective>2023-07-08T22:52:00-04:00</effective>
<expires>2023-07-09T22:00:00-04:00</expires>
<senderName>NWS Philadelphia - Mount Holly (New Jersey, Delaware, Southeastern Pennsylvania)</senderName>
<headline>Flood Watch issued July 09 at 2:59AM EDT  by NWS Philadelphia - Mount Holly</headline>
<description>...FLOOD WATCH IN EFFECT FROM 2 PM EDT THIS AFTERNOON THROUGH THIS
EVENING...
* WHAT...Flooding caused by excessive rainfall is possible.
* WHERE...Portions of Delaware...northeast Maryland...and southern
New Jersey...including the following areas...in Delaware...
Delaware Beaches, Inland Sussex, and Kent. In northeast Maryland...
Caroline and Talbot. In southern New Jersey...Atlantic, Atlantic
Coastal Cape May, Cape May, Coastal Atlantic, Coastal Ocean,
Cumberland, Ocean, and Southeastern Burlington.
* WHEN...From 2 PM EDT this afternoon through this evening.
* IMPACTS...Excessive runoff may result in flooding of rivers,
creeks, streams, and other low-lying and flood-prone locations.
* ADDITIONAL DETAILS...
- A slow moving line of thunderstorms is expected to cross the
region this afternoon and evening. Widespread rainfall
amounts of 1 to 2 inches are expected with localized amounts
of 3 to inches possible. These totals may result in flash
flooding especially in more urban locations.
- http://www.weather.gov/safety/flood</description>
<instruction>You should monitor later forecasts and be alert for possible Flood
Warnings. Those living in areas prone to flooding should be prepared
to take action should flooding develop.</instruction>
<parameter>
<valueName>WMOHEADER</valueName>
<value></value>
</parameter>
<parameter>
<valueName>UGC</valueName>
<value>DEZ002>004-MDZ019-020-NJZ020>027</value>
</parameter>
<parameter>
<valueName>VTEC</valueName>
<value>/O.EXB.KPHI.FA.A.0005.230709T1800Z-230710T0400Z/
/00000.0.ER.000000T0000Z.000000T0000Z.000000T0000Z.OO/</value>
</parameter>
<parameter>
<valueName>TIME...MOT...LOC</valueName>
<value></value>
</parameter>
<area>
<areaDesc>Caroline; Talbot</areaDesc>
<polygon></polygon>
<geocode>
<valueName>FIPS6</valueName>
<value>024011</value>
</geocode>
<geocode>
<valueName>FIPS6</valueName>
<value>024041</value>
</geocode>
<geocode>
<valueName>UGC</valueName>
<value>MDZ019</value>
</geocode>
<geocode>
<valueName>UGC</valueName>
<value>MDZ020</value>
</geocode>
</area>
</info>
</alert>