<?xml version = '1.0' encoding = 'UTF-8' standalone = 'yes'?>
<?xml-stylesheet href='capatomproduct.xsl' type='text/xsl'?>

<!--
This atom/xml feed is an index to active advisories, watches and warnings 
issued by the National Weather Service.  This index file is not the complete 
Common Alerting Protocol (CAP) alert message.  To obtain the complete CAP 
alert, please follow the links for each entry in this index.  Also note the 
CAP message uses a style sheet to convey the information in a human readable 
format.  Please view the source of the CAP message to see the complete data 
set.  Not all information in the CAP message is contained in this index of 
active alerts.
-->

<alert xmlns = 'urn:oasis:names:tc:emergency:cap:1.1'>

<!-- http-date = Tue, 12 Jul 2022 06:56:00 GMT -->
<identifier>NOAA-NWS-ALERTS-MD1264005DEF00.SevereThunderstormWarning.1264005E11C4MD.LWXSVRLWX.b11a5e12d6da18e44c664354007307c0</identifier>
<sender>w-nws.webmaster@noaa.gov</sender>
<sent>2022-07-12T14:56:00-04:00</sent>
<status>Actual</status>
<msgType>Alert</msgType>
<scope>Public</scope>
<note>Alert for Allegany (Maryland) Issued by the National Weather Service</note>
<info>
<category>Met</category>
<event>Severe Thunderstorm Warning</event>
<urgency>Immediate</urgency>
<severity>Severe</severity>
<certainty>Observed</certainty>
<eventCode>
<valueName>SAME</valueName>
<value>SVR</value>
</eventCode>
<effective>2022-07-12T14:56:00-04:00</effective>
<expires>2022-07-12T15:45:00-04:00</expires>
<senderName>NWS Baltimore/Washington (Washington D.C., Central Maryland, Northern Virginia, Eastern West Virginia)</senderName>
<headline>Severe Thunderstorm Warning issued July 12 at 2:56PM EDT until July 12 at 3:45PM EDT by NWS Baltimore/Washington</headline>
<description>The National Weather Service in Sterling Virginia has issued a
* Severe Thunderstorm Warning for...
Central Allegany County in western Maryland...
Northwestern Frederick County in northwestern Virginia...
West central Morgan County in the Panhandle of West Virginia...
Southeastern Mineral County in eastern West Virginia...
Hampshire County in eastern West Virginia...
* Until 345 PM EDT.
* At 256 PM EDT, severe thunderstorms were located along a line
extending from near La Vale to near Piedmont, moving southeast at
45 mph.
HAZARD...60 mph wind gusts and quarter size hail.
SOURCE...Radar indicated.
IMPACT...Damaging winds will cause some trees and large branches
to fall. This could injure those outdoors, as well as
damage homes and vehicles. Roadways may become blocked by
downed trees. Localized power outages are possible.
Unsecured light objects may become projectiles.
* Locations impacted include...
Romney, Paw Paw, Fort Ashby, Springfield, Capon Bridge, Green
Spring, Burlington, Oldtown, Spring Gap, Shanks, Fishers Bridge,
North Branch, Bloomery, Reeses Mill, Points, Delray, Junction,
Wapocomo, Augusta and Patterson Creek.
HAIL THREAT...RADAR INDICATED
MAX HAIL SIZE...1.00 IN
WIND THREAT...RADAR INDICATED
MAX WIND GUST...60 MPH</description>
<instruction>For your protection move to an interior room on the lowest floor of a
building.
Large hail and damaging winds and continuous cloud to ground
lightning is occurring with these storms. Move indoors immediately.
Lightning is one of nature`s leading killers. Remember, if you can
hear thunder, you are close enough to be struck by lightning.</instruction>
<parameter>
<valueName>WMOHEADER</valueName>
<value></value>
</parameter>
<parameter>
<valueName>UGC</valueName>
<value>MDC001-VAC069-WVC027-057-065</value>
</parameter>
<parameter>
<valueName>VTEC</valueName>
<value>/O.NEW.KLWX.SV.W.0242.220712T1856Z-220712T1945Z/</value>
</parameter>
<parameter>
<valueName>TIME...MOT...LOC</valueName>
<value>1856Z 297DEG 40KT 3963 7886 3944 7905</value>
</parameter>
<area>
<areaDesc>Allegany</areaDesc>
<polygon>39.56,-78.46 39.53,-78.32 39.46,-78.35 39.43,-78.35 39.41,-78.36 39.39,-78.35 39.14,-78.58 39.36,-78.99 39.62,-78.71 39.56,-78.46</polygon>
<geocode>
<valueName>FIPS6</valueName>
<value>024001</value>
</geocode>
<geocode>
<valueName>UGC</valueName>
<value>MDC001</value>
</geocode>
</area>
</info>
</alert>