<?xml version = '1.0' encoding = 'UTF-8' standalone = 'yes'?>
<?xml-stylesheet href='capatomproduct.xsl' type='text/xsl'?>

<!--
This atom/xml feed is an index to active advisories, watches and warnings 
issued by the National Weather Service.  This index file is not the complete 
Common Alerting Protocol (CAP) alert message.  To obtain the complete CAP 
alert, please follow the links for each entry in this index.  Also note the 
CAP message uses a style sheet to convey the information in a human readable 
format.  Please view the source of the CAP message to see the complete data 
set.  Not all information in the CAP message is contained in this index of 
active alerts.
-->

<alert xmlns = 'urn:oasis:names:tc:emergency:cap:1.1'>

<!-- http-date = Fri, 12 May 2023 01:24:00 GMT -->
<identifier>NOAA-NWS-ALERTS-NY1266487D4130.AirQualityAlert.1266488AF370NY.BUFAQABUF.a8a80f5543da8a3cb1e63e3a3309f357</identifier>
<sender>w-nws.webmaster@noaa.gov</sender>
<sent>2023-05-12T09:24:00-04:00</sent>
<status>Actual</status>
<msgType>Alert</msgType>
<scope>Public</scope>
<note>Alert for Jefferson; Monroe; Northern Cayuga; Oswego; Wayne (New York) Issued by the National Weather Service</note>
<info>
<category>Met</category>
<event>Air Quality Alert</event>
<urgency>Unknown</urgency>
<severity>Unknown</severity>
<certainty>Unknown</certainty>
<eventCode>
<valueName>SAME</valueName>
<value></value>
</eventCode>
<effective>2023-05-12T09:24:00-04:00</effective>
<expires>2023-05-12T23:00:00-04:00</expires>
<senderName>NWS Buffalo (Western New York)</senderName>
<headline>Air Quality Alert issued May 12 at 9:24AM EDT  by NWS Buffalo</headline>
<description>...AIR QUALITY ALERT IN EFFECT UNTIL 11 PM EDT THIS EVENING...
The New York State Department of Environmental Conservation at
Albany has issued an Air Quality Health Advisory for Ground Level
Ozone...until 11 PM EDT this evening.
Air quality levels in outdoor air are predicted to be greater than
an Air Quality Index value of 100 for Ground Level Ozone. The Air
Quality Index...or AQI...was created as an easy way to correlate
levels of different pollutants to one scale. The higher the AQI
value...the greater the health concern.
When pollution levels are elevated...the New York State Department
of Health recommends that individuals consider limiting strenuous
outdoor physical activity to reduce the risk of adverse health
effects. People who may be especially sensitive to the effects of
elevated levels of pollutants include the very young and those with
pre-existing respiratory problems such as asthma or heart disease.
Those with symptoms should consider consulting their personal
physician.
For additional information, please visit the New York State
Department of Environmental Conservation website at,
https://on.ny.gov/nyaqi, or call the Air Quality Hotline at
1 800 5 3 5, 1 3 4 5.</description>
<instruction></instruction>
<parameter>
<valueName>WMOHEADER</valueName>
<value></value>
</parameter>
<parameter>
<valueName>UGC</valueName>
<value>NYZ003>007</value>
</parameter>
<parameter>
<valueName>VTEC</valueName>
<value></value>
</parameter>
<parameter>
<valueName>TIME...MOT...LOC</valueName>
<value></value>
</parameter>
<area>
<areaDesc>Jefferson; Monroe; Northern Cayuga; Oswego; Wayne</areaDesc>
<polygon></polygon>
<geocode>
<valueName>FIPS6</valueName>
<value>036011</value>
</geocode>
<geocode>
<valueName>FIPS6</valueName>
<value>036045</value>
</geocode>
<geocode>
<valueName>FIPS6</valueName>
<value>036055</value>
</geocode>
<geocode>
<valueName>FIPS6</valueName>
<value>036075</value>
</geocode>
<geocode>
<valueName>FIPS6</valueName>
<value>036117</value>
</geocode>
<geocode>
<valueName>UGC</valueName>
<value>NYZ003</value>
</geocode>
<geocode>
<valueName>UGC</valueName>
<value>NYZ004</value>
</geocode>
<geocode>
<valueName>UGC</valueName>
<value>NYZ005</value>
</geocode>
<geocode>
<valueName>UGC</valueName>
<value>NYZ006</value>
</geocode>
<geocode>
<valueName>UGC</valueName>
<value>NYZ007</value>
</geocode>
</area>
</info>
</alert>