<?xml version = '1.0' encoding = 'UTF-8' standalone = 'yes'?>
<?xml-stylesheet href='capatomproduct.xsl' type='text/xsl'?>

<!--
This atom/xml feed is an index to active advisories, watches and warnings 
issued by the National Weather Service.  This index file is not the complete 
Common Alerting Protocol (CAP) alert message.  To obtain the complete CAP 
alert, please follow the links for each entry in this index.  Also note the 
CAP message uses a style sheet to convey the information in a human readable 
format.  Please view the source of the CAP message to see the complete data 
set.  Not all information in the CAP message is contained in this index of 
active alerts.
-->

<alert xmlns = 'urn:oasis:names:tc:emergency:cap:1.1'>

<!-- http-date = Thu, 17 Feb 2022 07:41:00 GMT -->
<identifier>NOAA-NWS-ALERTS-IN1263E2DCF674.FloodWarning.1263E3084A40IN.IWXFLSIWX.5d13c77a09b3eb7ca3f157954ee9f539</identifier>
<sender>w-nws.webmaster@noaa.gov</sender>
<sent>2022-02-17T14:41:00-05:00</sent>
<status>Actual</status>
<msgType>Alert</msgType>
<scope>Public</scope>
<note>Alert for Cass; Miami; Wabash (Indiana) Issued by the National Weather Service</note>
<info>
<category>Met</category>
<event>Flood Warning</event>
<urgency>Expected</urgency>
<severity>Moderate</severity>
<certainty>Likely</certainty>
<eventCode>
<valueName>SAME</valueName>
<value>FLW</value>
</eventCode>
<effective>2022-02-18T00:20:00-05:00</effective>
<expires>2022-02-19T22:36:00-05:00</expires>
<senderName>NWS NorthernIndiana (Northern Indiana and Northeastern Ohio)</senderName>
<headline>Flood Warning issued February 17 at 2:41PM EST until February 19 at 10:36PM EST by NWS NorthernIndiana</headline>
<description>...The Flood Warning is extended for the following rivers in
Indiana...
Wabash River near Linn Grove affecting Adams and Wells Counties.
Eel River at North Manchester affecting Cass IN, Miami, Wabash,
Whitley and Kosciusko Counties.
Yellow River at Plymouth affecting Marshall, Starke and St.
Joseph IN Counties.
...The Flood Warning continues for the following rivers in Indiana...
Salamonie River below Warren affecting Wabash, Huntington,
Blackford, Wells and Jay Counties.
Wabash River near Bluffton IN affecting Wells County.
Wabash River at Wabash affecting Cass IN, Miami and Wabash
Counties.
Salamonie River at Portland affecting Jay County.
Kankakee River at Davis affecting Starke, La Porte and St. Joseph
IN Counties.
.These river rises will shift ice within the river and could lead
to ice jams. This forecast is based on unobstructed flow and does
not factor additional rises associated with ice jams.
...FLOOD WARNING NOW IN EFFECT FROM LATE TONIGHT TO LATE SATURDAY
EVENING...
* WHAT...Minor flooding is forecast.
* WHERE...Wabash River at Wabash.
* WHEN...From late tonight to late Saturday evening.
* IMPACTS...At 14.0 feet, Lowland flooding begins in rural Wabash
County.
* ADDITIONAL DETAILS...
- At 1:30 PM EST Thursday the stage was 12.2 feet.
- Forecast...The river is expected to rise above flood stage
just after midnight tonight to a crest of 14.5 feet early
tomorrow afternoon. It will then fall below flood stage late
tomorrow evening.
- Flood stage is 14.0 feet.
- http://www.weather.gov/safety/flood
&amp;&amp;</description>
<instruction>Turn around, don`t drown when encountering flooded roads. Most flood
deaths occur in vehicles.
Please report observed flooding to local emergency services or law
enforcement and request they pass this information to the National
Weather Service when you can do so safely.
Detailed river forecasts and additional information can be found at
www.weather.gov/iwx under Rivers and Lakes.
This statement will be updated within the next 12 to 24 hours.</instruction>
<parameter>
<valueName>WMOHEADER</valueName>
<value></value>
</parameter>
<parameter>
<valueName>UGC</valueName>
<value>INC017-103-169</value>
</parameter>
<parameter>
<valueName>VTEC</valueName>
<value>/O.EXT.KIWX.FL.W.0016.220218T0520Z-220220T0336Z/
/WABI3.1.ER.220218T0520Z.220218T1800Z.220219T0336Z.NO/</value>
</parameter>
<parameter>
<valueName>TIME...MOT...LOC</valueName>
<value></value>
</parameter>
<area>
<areaDesc>Cass; Miami; Wabash</areaDesc>
<polygon>40.7,-86.18 40.78,-86.19 40.86,-85.7 40.81,-85.68 40.78,-85.82 40.7,-86.18</polygon>
<geocode>
<valueName>FIPS6</valueName>
<value>018017</value>
</geocode>
<geocode>
<valueName>FIPS6</valueName>
<value>018103</value>
</geocode>
<geocode>
<valueName>FIPS6</valueName>
<value>018169</value>
</geocode>
<geocode>
<valueName>UGC</valueName>
<value>INC017</value>
</geocode>
<geocode>
<valueName>UGC</valueName>
<value>INC103</value>
</geocode>
<geocode>
<valueName>UGC</valueName>
<value>INC169</value>
</geocode>
</area>
</info>
</alert>