<?xml version = '1.0' encoding = 'UTF-8' standalone = 'yes'?>
<?xml-stylesheet href='capatomproduct.xsl' type='text/xsl'?>

<!--
This atom/xml feed is an index to active advisories, watches and warnings 
issued by the National Weather Service.  This index file is not the complete 
Common Alerting Protocol (CAP) alert message.  To obtain the complete CAP 
alert, please follow the links for each entry in this index.  Also note the 
CAP message uses a style sheet to convey the information in a human readable 
format.  Please view the source of the CAP message to see the complete data 
set.  Not all information in the CAP message is contained in this index of 
active alerts.
-->

<alert xmlns = 'urn:oasis:names:tc:emergency:cap:1.1'>

<!-- http-date = Wed, 27 Jul 2022 08:15:00 GMT -->
<identifier>NOAA-NWS-ALERTS-NC126401430EDC.SpecialWeatherStatement.126401433010NC.MHXSPSMHX.d20c0b3fc3ac811c290d479a3c118eef</identifier>
<sender>w-nws.webmaster@noaa.gov</sender>
<sent>2022-07-27T16:15:00-04:00</sent>
<status>Actual</status>
<msgType>Alert</msgType>
<scope>Public</scope>
<note>Alert for Beaufort; Martin; Pitt (North Carolina) Issued by the National Weather Service</note>
<info>
<category>Met</category>
<event>Special Weather Statement</event>
<urgency>Expected</urgency>
<severity>Minor</severity>
<certainty>Observed</certainty>
<eventCode>
<valueName>SAME</valueName>
<value>SPS</value>
</eventCode>
<effective>2022-07-28T10:00:00-04:00</effective>
<expires>2022-07-27T17:00:00-04:00</expires>
<senderName>NWS Newport/Morehead City (Eastern North Carolina)</senderName>
<headline>Special Weather Statement issued July 27 at 4:15PM EDT  by NWS Newport/Morehead City</headline>
<description>...A strong thunderstorm will impact portions of southwestern
Washington, Pitt, Martin and northwestern Beaufort Counties through
500 PM EDT...
At 414 PM EDT, Doppler radar was tracking a strong thunderstorm near
Stokes, or 11 miles north of Greenville, moving southeast at 15 mph.
HAZARD...Wind gusts of 50 to 55 mph.
SOURCE...Radar indicated.
IMPACT...Gusty winds could knock down tree limbs and blow around
unsecured objects.
Locations impacted include...
Greenville, Washington, Winterville, Williamston, Bethel, Stokes,
Bell Arthur, Robersonville, Pactolus, House, Black Jack, Bruce, Old
Ford, Pitt Greenville Airport, Dowdy Ficklen Stadium, East Carolina
University, Gold Point, Jamesville, Grimesland and Simpson.
MAX HAIL SIZE...0.00 IN
MAX WIND GUST...55 MPH</description>
<instruction>If outdoors, consider seeking shelter inside a building.</instruction>
<parameter>
<valueName>WMOHEADER</valueName>
<value></value>
</parameter>
<parameter>
<valueName>UGC</valueName>
<value>NCZ029-044-080</value>
</parameter>
<parameter>
<valueName>VTEC</valueName>
<value></value>
</parameter>
<parameter>
<valueName>TIME...MOT...LOC</valueName>
<value>2014Z 315DEG 15KT 3575 7733</value>
</parameter>
<area>
<areaDesc>Beaufort; Martin; Pitt</areaDesc>
<polygon>35.89,-77.02 35.86,-77.04 35.86,-77.01 35.9,-76.92 35.83,-76.89 35.81,-76.9 35.85,-76.84 35.89,-76.83 35.87,-76.79 35.69,-76.84 35.49,-77.25 35.54,-77.54 35.73,-77.57 35.8,-77.47 35.83,-77.39 35.82,-77.35 35.88,-77.34 35.94,-77.2 35.93,-77.09 35.94,-77.05 35.89,-77.02</polygon>
<geocode>
<valueName>FIPS6</valueName>
<value>037013</value>
</geocode>
<geocode>
<valueName>FIPS6</valueName>
<value>037117</value>
</geocode>
<geocode>
<valueName>FIPS6</valueName>
<value>037147</value>
</geocode>
<geocode>
<valueName>UGC</valueName>
<value>NCZ029</value>
</geocode>
<geocode>
<valueName>UGC</valueName>
<value>NCZ044</value>
</geocode>
<geocode>
<valueName>UGC</valueName>
<value>NCZ080</value>
</geocode>
</area>
</info>
</alert>