<?xml version = '1.0' encoding = 'UTF-8' standalone = 'yes'?>
<?xml-stylesheet href='capatomproduct.xsl' type='text/xsl'?>

<!--
This atom/xml feed is an index to active advisories, watches and warnings 
issued by the National Weather Service.  This index file is not the complete 
Common Alerting Protocol (CAP) alert message.  To obtain the complete CAP 
alert, please follow the links for each entry in this index.  Also note the 
CAP message uses a style sheet to convey the information in a human readable 
format.  Please view the source of the CAP message to see the complete data 
set.  Not all information in the CAP message is contained in this index of 
active alerts.
-->

<alert xmlns = 'urn:oasis:names:tc:emergency:cap:1.1'>

<!-- http-date = Wed, 05 Apr 2023 01:53:00 GMT -->
<identifier>NOAA-NWS-ALERTS-AR1266421C9BC4.TornadoWarning.1266421CB9D8AR.LZKTORLZK.ef3b3b5ad0f9a45c45ddf04953cb4e92</identifier>
<sender>w-nws.webmaster@noaa.gov</sender>
<sent>2023-04-05T08:53:00-05:00</sent>
<status>Actual</status>
<msgType>Alert</msgType>
<scope>Public</scope>
<note>Alert for Logan; Scott; Yell (Arkansas) Issued by the National Weather Service</note>
<info>
<category>Met</category>
<event>Tornado Warning</event>
<urgency>Immediate</urgency>
<severity>Extreme</severity>
<certainty>Observed</certainty>
<eventCode>
<valueName>SAME</valueName>
<value>TOR</value>
</eventCode>
<effective>2023-04-05T08:53:00-05:00</effective>
<expires>2023-04-05T09:30:00-05:00</expires>
<senderName>NWS Little Rock (Arkansas)</senderName>
<headline>Tornado Warning issued April 05 at 8:53AM CDT until April 05 at 9:30AM CDT by NWS Little Rock</headline>
<description>The National Weather Service in Little Rock has issued a
* Tornado Warning for...
Southeastern Logan County in western Arkansas...
East central Scott County in western Arkansas...
Northwestern Yell County in central Arkansas...
* Until 930 AM CDT.
* At 853 AM CDT, a severe thunderstorm capable of producing a tornado
was located over Stonehouse Recreation Area, or 14 miles southeast
of Booneville, moving northeast at 55 mph.
HAZARD...Tornado and quarter size hail.
SOURCE...Radar indicated rotation.
IMPACT...Flying debris will be dangerous to those caught without
shelter. Mobile homes will be damaged or destroyed.
Damage to roofs, windows, and vehicles will occur.  Tree
damage is likely.
* Locations impacted include...
Danville...                       Stonehouse Recreation Area...
Mount Magazine...                 Belleville...
Havana...                         Corinth...
Ranger...                         Macedonia in Yell County...
Waveland...                       Waltreak...
Kingston...                       Blue Ball...
Spring Lake Campground...
TORNADO...RADAR INDICATED
MAX HAIL SIZE...1.00 IN</description>
<instruction>TAKE COVER NOW! Move to a basement or an interior room on the lowest
floor of a sturdy building. Avoid windows. If you are outdoors, in a
mobile home, or in a vehicle, move to the closest substantial shelter
and protect yourself from flying debris.</instruction>
<parameter>
<valueName>WMOHEADER</valueName>
<value></value>
</parameter>
<parameter>
<valueName>UGC</valueName>
<value>ARC083-127-149</value>
</parameter>
<parameter>
<valueName>VTEC</valueName>
<value>/O.NEW.KLZK.TO.W.0072.230405T1353Z-230405T1430Z/</value>
</parameter>
<parameter>
<valueName>TIME...MOT...LOC</valueName>
<value>1353Z 242DEG 48KT 3501 9371</value>
</parameter>
<area>
<areaDesc>Logan; Scott; Yell</areaDesc>
<polygon>35.05,-93.84 35.3,-93.37 35.02,-93.24 34.92,-93.75 35.05,-93.84</polygon>
<geocode>
<valueName>FIPS6</valueName>
<value>005083</value>
</geocode>
<geocode>
<valueName>FIPS6</valueName>
<value>005127</value>
</geocode>
<geocode>
<valueName>FIPS6</valueName>
<value>005149</value>
</geocode>
<geocode>
<valueName>UGC</valueName>
<value>ARC083</value>
</geocode>
<geocode>
<valueName>UGC</valueName>
<value>ARC127</value>
</geocode>
<geocode>
<valueName>UGC</valueName>
<value>ARC149</value>
</geocode>
</area>
</info>
</alert>