<?xml version = '1.0' encoding = 'UTF-8' standalone = 'yes'?>
<?xml-stylesheet href='capatomproduct.xsl' type='text/xsl'?>

<!--
This atom/xml feed is an index to active advisories, watches and warnings 
issued by the National Weather Service.  This index file is not the complete 
Common Alerting Protocol (CAP) alert message.  To obtain the complete CAP 
alert, please follow the links for each entry in this index.  Also note the 
CAP message uses a style sheet to convey the information in a human readable 
format.  Please view the source of the CAP message to see the complete data 
set.  Not all information in the CAP message is contained in this index of 
active alerts.
-->

<alert xmlns = 'urn:oasis:names:tc:emergency:cap:1.1'>

<!-- http-date = Thu, 22 Sep 2022 01:59:00 GMT -->
<identifier>NOAA-NWS-ALERTS-OH12640CE1855C.BeachHazardsStatement.12640CF0D7A0OH.CLECFWCLE.b041312fc841689f9bfbbd6ded94bcc0</identifier>
<sender>w-nws.webmaster@noaa.gov</sender>
<sent>2022-09-22T09:59:00-04:00</sent>
<status>Actual</status>
<msgType>Alert</msgType>
<scope>Public</scope>
<note>Alert for Cuyahoga; Erie; Lorain; Ottawa (Ohio) Issued by the National Weather Service</note>
<info>
<category>Met</category>
<event>Beach Hazards Statement</event>
<urgency>Expected</urgency>
<severity>Moderate</severity>
<certainty>Likely</certainty>
<eventCode>
<valueName>SAME</valueName>
<value></value>
</eventCode>
<effective>2022-09-22T09:59:00-04:00</effective>
<expires>2022-09-23T10:00:00-04:00</expires>
<senderName>NWS Cleveland (Northern Ohio)</senderName>
<headline>Beach Hazards Statement issued September 22 at 9:59AM EDT until September 23 at 10:00AM EDT by NWS Cleveland</headline>
<description>...BEACH HAZARDS STATEMENT REMAINS IN EFFECT THROUGH FRIDAY
MORNING...
* WHAT...High risk of rip currents.
* WHERE...Ottawa County.
* WHEN...Through Friday morning.
* IMPACTS...Wind and wave action will cause currents on the
lakeshore. Swimmers should not enter the water. Currents can
carry swimmers away from shore through a sand bar and along
structures extending out into the lake.</description>
<instruction>Remain out of the water to avoid hazardous swimming conditions.</instruction>
<parameter>
<valueName>WMOHEADER</valueName>
<value></value>
</parameter>
<parameter>
<valueName>UGC</valueName>
<value>OHZ007-009>011</value>
</parameter>
<parameter>
<valueName>VTEC</valueName>
<value>/O.CON.KCLE.BH.S.0024.000000T0000Z-220923T1400Z/</value>
</parameter>
<parameter>
<valueName>TIME...MOT...LOC</valueName>
<value></value>
</parameter>
<area>
<areaDesc>Cuyahoga; Erie; Lorain; Ottawa</areaDesc>
<polygon></polygon>
<geocode>
<valueName>FIPS6</valueName>
<value>039035</value>
</geocode>
<geocode>
<valueName>FIPS6</valueName>
<value>039043</value>
</geocode>
<geocode>
<valueName>FIPS6</valueName>
<value>039093</value>
</geocode>
<geocode>
<valueName>FIPS6</valueName>
<value>039123</value>
</geocode>
<geocode>
<valueName>UGC</valueName>
<value>OHZ007</value>
</geocode>
<geocode>
<valueName>UGC</valueName>
<value>OHZ009</value>
</geocode>
<geocode>
<valueName>UGC</valueName>
<value>OHZ010</value>
</geocode>
<geocode>
<valueName>UGC</valueName>
<value>OHZ011</value>
</geocode>
</area>
</info>
</alert>