<?xml version = '1.0' encoding = 'UTF-8' standalone = 'yes'?>
<?xml-stylesheet href='capatomproduct.xsl' type='text/xsl'?>

<!--
This atom/xml feed is an index to active advisories, watches and warnings 
issued by the National Weather Service.  This index file is not the complete 
Common Alerting Protocol (CAP) alert message.  To obtain the complete CAP 
alert, please follow the links for each entry in this index.  Also note the 
CAP message uses a style sheet to convey the information in a human readable 
format.  Please view the source of the CAP message to see the complete data 
set.  Not all information in the CAP message is contained in this index of 
active alerts.
-->

<alert xmlns = 'urn:oasis:names:tc:emergency:cap:1.1'>

<!-- http-date = Wed, 15 Dec 2021 08:21:00 GMT -->
<identifier>NOAA-NWS-ALERTS-TX1261CA4BA274.RedFlagWarning.1261CA59A400TX.AMARFWAMA.40ddfcbf6131674f7568cd0515fd484a</identifier>
<sender>w-nws.webmaster@noaa.gov</sender>
<sent>2021-12-15T02:21:00-06:00</sent>
<status>Actual</status>
<msgType>Alert</msgType>
<scope>Public</scope>
<note>Alert for Dallam; Hansford; Hartley; Ochiltree; Sherman (Texas) Issued by the National Weather Service</note>
<info>
<category>Met</category>
<event>Red Flag Warning</event>
<urgency>Expected</urgency>
<severity>Severe</severity>
<certainty>Likely</certainty>
<eventCode>
<valueName>SAME</valueName>
<value>FRW</value>
</eventCode>
<effective>2021-12-15T09:00:00-06:00</effective>
<expires>2021-12-15T18:00:00-06:00</expires>
<senderName>NWS Amarillo (the Texas Panhandle)</senderName>
<headline>Red Flag Warning issued December 15 at 2:21AM CST until December 15 at 6:00PM CST by NWS Amarillo</headline>
<description>...RED FLAG WARNING REMAINS IN EFFECT FROM 9 AM THIS MORNING TO
6 PM CST THIS EVENING FOR STRONG WINDS AND LOW RELATIVE HUMIDITY
FOR THE EASTERN OKLAHOMA PANHANDLE AND NORTH CENTRAL TEXAS
PANHANDLE...
* Affected Area...In Oklahoma...Cimarron...Texas and Beaver. In
Texas...Dallam...Sherman...Hansford...Ochiltree and Hartley.
* 20 Foot Winds...Southwest 35 to 45 mph with gusts up to 65 mph.
* Relative Humidity...As low as 8 percent.
* Red Flag Threat Index...Values between 3 and 7 are expected
across a majority of the Panhandles, with values of 8 possible
in the Oklahoma and northern Texas Panhandles.
* Timing...Wednesday morning through the late afternoon hours.</description>
<instruction>A Red Flag Warning means that critical fire weather conditions
are either occurring now...or will shortly. A combination of
strong winds...low relative humidity...and warm temperatures will
create favorable weather for rapid fire growth and spread. Avoid
activities that promote open flames and sparks.</instruction>
<parameter>
<valueName>WMOHEADER</valueName>
<value></value>
</parameter>
<parameter>
<valueName>UGC</valueName>
<value>OKZ001>003-TXZ001>004-006</value>
</parameter>
<parameter>
<valueName>VTEC</valueName>
<value>/O.CON.KAMA.FW.W.0022.211215T1500Z-211216T0000Z/</value>
</parameter>
<parameter>
<valueName>TIME...MOT...LOC</valueName>
<value></value>
</parameter>
<area>
<areaDesc>Dallam; Hansford; Hartley; Ochiltree; Sherman</areaDesc>
<polygon></polygon>
<geocode>
<valueName>FIPS6</valueName>
<value>048111</value>
</geocode>
<geocode>
<valueName>FIPS6</valueName>
<value>048195</value>
</geocode>
<geocode>
<valueName>FIPS6</valueName>
<value>048205</value>
</geocode>
<geocode>
<valueName>FIPS6</valueName>
<value>048357</value>
</geocode>
<geocode>
<valueName>FIPS6</valueName>
<value>048421</value>
</geocode>
<geocode>
<valueName>UGC</valueName>
<value>TXZ001</value>
</geocode>
<geocode>
<valueName>UGC</valueName>
<value>TXZ002</value>
</geocode>
<geocode>
<valueName>UGC</valueName>
<value>TXZ003</value>
</geocode>
<geocode>
<valueName>UGC</valueName>
<value>TXZ004</value>
</geocode>
<geocode>
<valueName>UGC</valueName>
<value>TXZ006</value>
</geocode>
</area>
</info>
</alert>