<?xml version = '1.0' encoding = 'UTF-8' standalone = 'yes'?>
<?xml-stylesheet href='capatomproduct.xsl' type='text/xsl'?>

<!--
This atom/xml feed is an index to active advisories, watches and warnings 
issued by the National Weather Service.  This index file is not the complete 
Common Alerting Protocol (CAP) alert message.  To obtain the complete CAP 
alert, please follow the links for each entry in this index.  Also note the 
CAP message uses a style sheet to convey the information in a human readable 
format.  Please view the source of the CAP message to see the complete data 
set.  Not all information in the CAP message is contained in this index of 
active alerts.
-->

<alert xmlns = 'urn:oasis:names:tc:emergency:cap:1.1'>

<!-- http-date = Thu, 16 Nov 2023 09:11:00 GMT -->
<identifier>NOAA-NWS-ALERTS-WI12666C7CEEDC.SpecialWeatherStatement.12666C7DFC00WI.DLHSPSDLH.42d03ec12a9b765e558d43510aa8e078</identifier>
<sender>w-nws.webmaster@noaa.gov</sender>
<sent>2023-11-16T03:11:00-06:00</sent>
<status>Actual</status>
<msgType>Alert</msgType>
<scope>Public</scope>
<note>Alert for Burnett; Douglas; Sawyer; Washburn (Wisconsin) Issued by the National Weather Service</note>
<info>
<category>Met</category>
<event>Special Weather Statement</event>
<urgency>Expected</urgency>
<severity>Minor</severity>
<certainty>Observed</certainty>
<eventCode>
<valueName>SAME</valueName>
<value>SPS</value>
</eventCode>
<effective>2023-11-16T03:11:00-06:00</effective>
<expires>2023-11-16T10:00:00-06:00</expires>
<senderName>NWS Duluth (Northeast Minnesota and Northern Wisconsin)</senderName>
<headline>Special Weather Statement issued November 16 at 3:11AM CST  by NWS Duluth</headline>
<description>...GUSTY SOUTHWEST WINDS EXPECTED TODAY...
Gusty southwest winds are expected across northwest Wisconsin
today with speeds from 15 to 25 mph and gusts to 40 mph,
especially this afternoon. A few wind gusts approaching 45 mph may
be possible. Exercise caution if driving high profile vehicles,
especially in open areas and across bridges and overpasses. The
gusty winds are expected to gradually lessen this evening.</description>
<instruction></instruction>
<parameter>
<valueName>WMOHEADER</valueName>
<value></value>
</parameter>
<parameter>
<valueName>UGC</valueName>
<value>WIZ001-006>008</value>
</parameter>
<parameter>
<valueName>VTEC</valueName>
<value></value>
</parameter>
<parameter>
<valueName>TIME...MOT...LOC</valueName>
<value></value>
</parameter>
<area>
<areaDesc>Burnett; Douglas; Sawyer; Washburn</areaDesc>
<polygon></polygon>
<geocode>
<valueName>FIPS6</valueName>
<value>055013</value>
</geocode>
<geocode>
<valueName>FIPS6</valueName>
<value>055031</value>
</geocode>
<geocode>
<valueName>FIPS6</valueName>
<value>055113</value>
</geocode>
<geocode>
<valueName>FIPS6</valueName>
<value>055129</value>
</geocode>
<geocode>
<valueName>UGC</valueName>
<value>WIZ001</value>
</geocode>
<geocode>
<valueName>UGC</valueName>
<value>WIZ006</value>
</geocode>
<geocode>
<valueName>UGC</valueName>
<value>WIZ007</value>
</geocode>
<geocode>
<valueName>UGC</valueName>
<value>WIZ008</value>
</geocode>
</area>
</info>
</alert>